Metadata-Version: 2.1
Name: HAlphaAnomalyzer
Version: 1.1.0
Summary: "This software identifies anomalous H-Alpha observations."
Home-page: UNKNOWN
Author: "Mahsa Khazaei, Heba Mahdi, Azim Ahmadzadeh"
Author-email: "mkdgy@umsystem.edu"
License: UNKNOWN
Platform: UNKNOWN
Classifier: License :: OSI Approved :: GNU General Public License v3 or later (GPLv3+)
Requires-Python: >=3.10
